README.rst
setup.py
cfpp/__init__.py
cfpp/__main__.py
cfpp/_version.py
cfpp/extrinsics.py
cfpp.egg-info/PKG-INFO
cfpp.egg-info/SOURCES.txt
cfpp.egg-info/dependency_links.txt
cfpp.egg-info/entry_points.txt
cfpp.egg-info/not-zip-safe
cfpp.egg-info/requires.txt
cfpp.egg-info/top_level.txt