Metadata-Version: 1.1
Name: cfpp
Version: 0.1.2
Summary: Adds helpful "extrinsic" functions to CloudFormation templates.
Home-page: https://github.com/dcoker/cfpp/
Author: Doug Coker
Author-email: dcoker@gmail.com
License: https://www.apache.org/licenses/LICENSE-2.0
Platform: UNKNOWN
Classifier: Development Status :: 3 - Alpha
Classifier: Environment :: Console
Classifier: Intended Audience :: Developers
Classifier: License :: OSI Approved :: Apache Software License
Classifier: Programming Language :: Python :: 2.7
